nord_config_generator/__init__.py
nord_config_generator/main.py
nord_config_generator/ui.py
nord_config_generator-1.0.4.dist-info/METADATA
nord_config_generator-1.0.4.dist-info/WHEEL
nord_config_generator-1.0.4.dist-info/entry_points.txt
nord_config_generator-1.0.4.dist-info/top_level.txt
nord_config_generator-1.0.4.dist-info/RECORD
